apollov2/__init__.py
apollov2/api_parser.py
apollov2_football_api_parser-0.0.4.dist-info/LICENSE
apollov2_football_api_parser-0.0.4.dist-info/METADATA
apollov2_football_api_parser-0.0.4.dist-info/WHEEL
apollov2_football_api_parser-0.0.4.dist-info/top_level.txt
apollov2_football_api_parser-0.0.4.dist-info/RECORD
