Metadata-Version: 2.1
Name: apollov2-football-api-parser
Version: 0.0.4
Summary: extract data from api and transform it into dataframe
Author: zhe wang
Classifier: Programming Language :: Python :: 3
Classifier: License :: OSI Approved :: MIT License
Classifier: Operating System :: OS Independent
Requires-Python: >=3.6
License-File: LICENSE
